votemarket_toolkit/__init__.py
votemarket_toolkit/analytics/__init__.py
votemarket_toolkit/analytics/models.py
votemarket_toolkit/analytics/service.py
votemarket_toolkit/campaigns/__init__.py
votemarket_toolkit/campaigns/models.py
votemarket_toolkit/campaigns/service.py
votemarket_toolkit/contracts/__init__.py
votemarket_toolkit/contracts/compiler.py
votemarket_toolkit/contracts/reader.py
votemarket_toolkit/data/__init__.py
votemarket_toolkit/data/eligibility.py
votemarket_toolkit/data/oracle.py
votemarket_toolkit/proofs/__init__.py
votemarket_toolkit/proofs/manager.py
votemarket_toolkit/proofs/types.py
votemarket_toolkit/proofs/user_eligibility_service.py
votemarket_toolkit/proofs/generators/__init__.py
votemarket_toolkit/proofs/generators/block_info.py
votemarket_toolkit/proofs/generators/gauge_proof.py
votemarket_toolkit/proofs/generators/user_proof.py
votemarket_toolkit/resources/__init__.py
votemarket_toolkit/resources/abi/__init__.py
votemarket_toolkit/resources/abi/campaign_remote_manager.json
votemarket_toolkit/resources/abi/ccip_adapter.json
votemarket_toolkit/resources/abi/ccip_router.json
votemarket_toolkit/resources/abi/erc20.json
votemarket_toolkit/resources/abi/gauge_controller.json
votemarket_toolkit/resources/abi/laposte.json
votemarket_toolkit/resources/abi/lens_oracle.json
votemarket_toolkit/resources/abi/mock_verifier.json
votemarket_toolkit/resources/abi/oracle.json
votemarket_toolkit/resources/abi/oracle_lens.json
votemarket_toolkit/resources/abi/pendle_gauge_controller.json
votemarket_toolkit/resources/abi/registry.json
votemarket_toolkit/resources/abi/router.json
votemarket_toolkit/resources/abi/tokenfactory.json
votemarket_toolkit/resources/abi/verifier.json
votemarket_toolkit/resources/abi/vm_platform.json
votemarket_toolkit/resources/abi/yb_gauge_controller.json
votemarket_toolkit/resources/bytecodes/BatchCampaignsWithPeriods.json
votemarket_toolkit/resources/bytecodes/GetActiveCampaignIds.json
votemarket_toolkit-2.0.0.dist-info/METADATA
votemarket_toolkit-2.0.0.dist-info/WHEEL
votemarket_toolkit-2.0.0.dist-info/licenses/LICENSE
votemarket_toolkit-2.0.0.dist-info/RECORD
