Metadata-Version: 2.4
Name: votemarket-toolkit
Version: 2.0.0
Summary: Python SDK for VoteMarket - campaign management, proofs, and analytics
Project-URL: Homepage, https://github.com/stake-dao/votemarket-proof-toolkit
Project-URL: Repository, https://github.com/stake-dao/votemarket-proof-toolkit
Project-URL: Issues, https://github.com/stake-dao/votemarket-proof-toolkit/issues
Project-URL: Documentation, https://github.com/stake-dao/votemarket-proof-toolkit/tree/main/docs
Author-email: Stake DAO <admin@stakedao.org>
License: AGPL-3.0
License-File: LICENSE
Keywords: dao,defi,ethereum,votemarket,voting
Classifier: Development Status :: 4 - Beta
Classifier: Intended Audience :: Developers
Classifier: License :: OSI Approved :: GNU Affero General Public License v3
Classifier: Programming Language :: Python :: 3
Classifier: Programming Language :: Python :: 3.10
Classifier: Programming Language :: Python :: 3.11
Classifier: Programming Language :: Python :: 3.12
Classifier: Topic :: Office/Business :: Financial
Classifier: Topic :: Software Development :: Libraries :: Python Modules
Requires-Python: <4,>=3.10
Requires-Dist: cmake>=3.30.5
Requires-Dist: eth-utils>=5.1.0
Requires-Dist: fastparquet>=2024.5.0
Requires-Dist: httpx>=0.28.1
Requires-Dist: pandas>=2.0.0
Requires-Dist: py-solc-x>=2.0.3
Requires-Dist: pyarrow>=17.0.0
Requires-Dist: python-dotenv>=1.0.1
Requires-Dist: rich>=13.7.0
Requires-Dist: w3multicall>=0.3.1
Requires-Dist: web3>=7.12.0
Provides-Extra: dev
Requires-Dist: black>=24.1.0; extra == 'dev'
Requires-Dist: pytest-asyncio>=0.23.0; extra == 'dev'
Requires-Dist: pytest-cov>=4.1.0; extra == 'dev'
Requires-Dist: pytest>=8.0.0; extra == 'dev'
Requires-Dist: ruff>=0.7.4; extra == 'dev'
